smbgym/__init__.py
smbgym/_registration.py
smbgym/bridge.py
smbgym/env.py
smbgym/bin/ap.jar
smbgym/helper/__init__.py
smbgym/helper/encode.py
smbgym/original/lvl-1.txt
smbgym/original/lvl-10.txt
smbgym/original/lvl-11.txt
smbgym/original/lvl-12.txt
smbgym/original/lvl-13.txt
smbgym/original/lvl-14.txt
smbgym/original/lvl-15.txt
smbgym/original/lvl-2.txt
smbgym/original/lvl-3.txt
smbgym/original/lvl-4.txt
smbgym/original/lvl-5.txt
smbgym/original/lvl-6.txt
smbgym/original/lvl-7.txt
smbgym/original/lvl-8.txt
smbgym/original/lvl-9.txt
smbgym-0.0.3.dist-info/METADATA
smbgym-0.0.3.dist-info/WHEEL
smbgym-0.0.3.dist-info/licenses/LICENSE
smbgym-0.0.3.dist-info/RECORD
